dsa_reg/__init__.py
dsa_reg-1.1.4.dist-info/LICENSE
dsa_reg-1.1.4.dist-info/METADATA
dsa_reg-1.1.4.dist-info/WHEEL
dsa_reg-1.1.4.dist-info/top_level.txt
dsa_reg-1.1.4.dist-info/RECORD
