Metadata-Version: 2.1
Name: dsa-reg
Version: 1.1.4
Summary: Register DSA items thumbnails and return homography matrix, image size,  x offset, y offset, scale x, and scale y. The registration code is based on OpenCV
Home-page: http://github.com/mmasoud1/dsa_reg.git
Author: Mohamed Masoud
Author-email: mmasoud2@outlook.com
License: MIT
Platform: UNKNOWN
Requires-Python: >=2.7
Requires-Dist: girder-client
Requires-Dist: six
Requires-Dist: Pillow
Requires-Dist: opencv-python
Requires-Dist: scikit-image
